example_package_for_flf/__init__.py
example_package_for_flf/_version.py
example_package_for_flf/core.py
does_it_fit-0.0.1.dist-info/LICENSE
does_it_fit-0.0.1.dist-info/METADATA
does_it_fit-0.0.1.dist-info/WHEEL
does_it_fit-0.0.1.dist-info/top_level.txt
does_it_fit-0.0.1.dist-info/RECORD
