Metadata-Version: 2.1
Name: does-it-fit
Version: 0.0.1
Summary: A python package that checks if shapes positioned on the circumference of a circle overlap or not
Home-page: https://github.com/shimwell/example_package_for_flf
Author: Jonathan Shimwell
Author-email: jonathan.shimwell@firstlightfusion.com
License: MIT
Project-URL: Source, https://github.com/shimwell/example_package_for_flf
Project-URL: Tracker, https://github.com/shimwell/example_package_for_flf/issues
Classifier: Natural Language :: English
Classifier: Topic :: Scientific/Engineering
Classifier: Programming Language :: Python :: 3
Classifier: Programming Language :: Python :: 3.7
Classifier: Programming Language :: Python :: 3.8
Classifier: Programming Language :: Python :: 3.9
Classifier: Programming Language :: Python :: 3.10
Classifier: License :: OSI Approved :: MIT License
Classifier: Operating System :: OS Independent
Requires-Python: >=3.6
License-File: LICENSE
Provides-Extra: tests
Requires-Dist: pytest (>=5.4.3) ; extra == 'tests'
